{
  "oppdatert": "2026-04-09",
  "kupongar": [
    {
      "id": "e5178f5b-ddec-4f37-8507-a6edd07d7afa",
      "butikk": "Kiwi",
      "beskriving": "10% rabatt",
      "kode": "KIWI10",
      "utl?per": "2024-04-29",
      "kjelde": "epost",
      "lagt_til": "2026-04-08"
    },
    {
      "id": "855e89c1-4e05-4df1-ae72-e23c4b817016",
      "butikk": "Clas Ohlson",
      "beskriving": "-20 % p? rengj?ringsprodukter fra Jif (Klubbpris)",
      "kode": null,
      "utl?per": null,
      "kjelde": "epost",
      "lagt_til": "2026-04-08"
    },
    {
      "id": "dd4a4b4d-ed55-470d-aeb5-d21c15cfac74",
      "butikk": "Elico",
      "beskriving": "15 % rabatt p? hele bestillingen",
      "kode": "EASTER15",
      "utl?per": null,
      "kjelde": "epost",
      "lagt_til": "2026-04-08"
    },
    {
      "id": "9f4a5bd0-a119-4273-8ed7-b13387c8b253",
      "butikk": "Barnas Hus",
      "beskriving": "Opptil -40% p? bestselgere til baby",
      "kode": null,
      "utl?per": null,
      "kjelde": "epost",
      "lagt_til": "2026-04-08"
    },
    {
      "id": "e192f3eb-94f6-4b03-a954-fe7639fdd8b3",
      "butikk": "Kid",
      "beskriving": "50% p? sengesett, dundyner, laken og sengetepper",
      "kode": null,
      "utl?per": null,
      "kjelde": "epost",
      "lagt_til": "2026-04-08"
    },
    {
      "id": "42861e92-baf0-446a-a509-24a9b9be4a57",
      "butikk": "Kid",
      "beskriving": "50% p? gardiner og pynteputer",
      "kode": null,
      "utl?per": null,
      "kjelde": "epost",
      "lagt_til": "2026-04-08"
    },
    {
      "id": "b41e7915-64a9-4267-afa1-2df4c58a249b",
      "butikk": "MENY",
      "beskriving": "F? 5% Trumf-bonus p? netthandel og levering.",
      "kode": null,
      "utl?per": "2024-04-30",
      "kjelde": "epost",
      "lagt_til": "2026-04-08"
    },
    {
      "id": "eead85b7-dbef-41f0-b0db-5957d9979e1d",
      "butikk": "MENY",
      "beskriving": "Tilbud p? Evergood, Jarlsberg og pizza-produkter.",
      "kode": null,
      "utl?per": null,
      "kjelde": "epost",
      "lagt_til": "2026-04-08"
    },
    {
      "id": "59252c52-dd48-44cd-a963-d00f5ad8a48d",
      "butikk": "Georg Jensen Damask",
      "beskriving": "Sun Stripe badelagen og matchende tote bag til introduksjonspris (290 DKK, normalpris 485 DKK)",
      "kode": null,
      "utl?per": null,
      "kjelde": "epost",
      "lagt_til": "2026-04-08"
    },
    {
      "id": "24b7d03a-c8f2-406b-8f96-895e47f1f390",
      "butikk": "Barnas Hus",
      "beskriving": "Body og pysj til 59,- / 89,-",
      "kode": null,
      "utl?per": null,
      "kjelde": "epost",
      "lagt_til": "2026-04-08"
    },
    {
      "id": "c261d348-9e18-4122-b148-8d8259df1ccb",
      "butikk": "Clas Ohlson",
      "beskriving": "-20% på rengjøringsprodukter fra Jif (Klubbpris)",
      "kode": null,
      "utløper": null,
      "kjelde": "epost",
      "lagt_til": "2026-04-08"
    },
    {
      "id": "bc6920b2-60c8-4fe4-b8d2-b010e4f2780b",
      "butikk": "Elkjøp",
      "beskriving": "Spar opptil 61% på TV-er under vårsalget.",
      "kode": null,
      "utløper": null,
      "kjelde": "epost",
      "lagt_til": "2026-04-08"
    },
    {
      "id": "2656fe61-81c7-4818-b12b-0edcd769f393",
      "butikk": "Elkjøp",
      "beskriving": "Spar opptil 40% på mobiltelefoner under vårsalget.",
      "kode": null,
      "utløper": null,
      "kjelde": "epost",
      "lagt_til": "2026-04-08"
    },
    {
      "id": "bbb9e1ba-2b3c-4a5c-a3e2-e067350f021e",
      "butikk": "Elkjøp",
      "beskriving": "Gode priser på PC-er og andre produkter under vårsalget.",
      "kode": null,
      "utløper": null,
      "kjelde": "epost",
      "lagt_til": "2026-04-08"
    },
    {
      "id": "404a8708-0aa9-42d4-9c28-451791797201",
      "butikk": "Klint",
      "beskriving": "Tilbud på startpakke med utvalgte produkter",
      "kode": "STARTERKIT",
      "utløper": null,
      "kjelde": "epost",
      "lagt_til": "2026-04-08"
    },
    {
      "id": "11c870b1-3ae8-44cd-b5e9-97ad1c0bf585",
      "butikk": "Norwegian",
      "beskriving": "Få 3x Spenn (bonuspoeng/cashback) på alle flyreiser med Norwegian for reiser i perioden 07.04.2026 - 30.08.2026.",
      "kode": "SUPERSPENN",
      "utløper": null,
      "kjelde": "epost",
      "lagt_til": "2026-04-08"
    },
    {
      "id": "5e330297-b6ab-4407-910a-452ab4b83df2",
      "butikk": "Komplett",
      "beskriving": "10% rabatt på alle demovarer",
      "kode": null,
      "utløper": "2027-04-02",
      "kjelde": "epost",
      "lagt_til": "2026-04-08"
    },
    {
      "id": "89c6c2d0-6763-4bf7-8208-246b4213e4f3",
      "butikk": "Komplett",
      "beskriving": "Fri frakt for medlemmer",
      "kode": null,
      "utløper": null,
      "kjelde": "epost",
      "lagt_til": "2026-04-08"
    },
    {
      "id": "ce9274fb-e959-4fd8-b085-bb6ebeac21b8",
      "butikk": "Elico",
      "beskriving": "15 % rabatt på hele bestillingen",
      "kode": "EASTER15",
      "utløper": null,
      "kjelde": "epost",
      "lagt_til": "2026-04-08"
    },
    {
      "id": "1be68865-56b9-47c9-81ed-57695f78d8fc",
      "butikk": "Barnas Hus",
      "beskriving": "Opptil -40% på bestselgere til baby",
      "kode": null,
      "utløper": null,
      "kjelde": "epost",
      "lagt_til": "2026-04-08"
    },
    {
      "id": "f85b7a39-187d-4594-9f6f-5161628afc39",
      "butikk": "Kid",
      "beskriving": "50% på sengesett, dundyner, laken og sengetepper",
      "kode": null,
      "utløper": null,
      "kjelde": "epost",
      "lagt_til": "2026-04-08"
    },
    {
      "id": "1b4f375f-0e1f-4956-9e37-7171c529d342",
      "butikk": "Kid",
      "beskriving": "50% på gardiner og pynteputer",
      "kode": null,
      "utløper": null,
      "kjelde": "epost",
      "lagt_til": "2026-04-08"
    },
    {
      "id": "8a097a88-3cd5-488a-a2f1-903b444014c8",
      "butikk": "MENY",
      "beskriving": "Tilbud på Evergood, Jarlsberg og pizza-produkter",
      "kode": null,
      "utløper": null,
      "kjelde": "epost",
      "lagt_til": "2026-04-08"
    },
    {
      "id": "b55a2848-f7e3-46a0-8d28-613c881bd09b",
      "butikk": "Georg Jensen Damask",
      "beskriving": "Sun Stripe badelagen og matchende tote bag til introduktionspris. Normalpris 485 DKK, introduktionspris 290 DKK.",
      "kode": null,
      "utløper": null,
      "kjelde": "epost",
      "lagt_til": "2026-04-08"
    },
    {
      "id": "715fb152-1137-4877-b24b-448e48506835",
      "butikk": "Clas Ohlson",
      "beskriving": "-20 % på rengjøringsprodukter fra Jif (klubbpris)",
      "kode": null,
      "utløper": null,
      "kjelde": "epost",
      "lagt_til": "2026-04-08"
    },
    {
      "id": "9906050c-b196-4aef-9bea-ac60cc26a54e",
      "butikk": "Elkjøp",
      "beskriving": "Opptil 61% rabatt på TV-er under Vårsalget.",
      "kode": null,
      "utløper": null,
      "kjelde": "epost",
      "lagt_til": "2026-04-08"
    },
    {
      "id": "c8f279c7-68b4-420f-8eb2-57e67f094e7b",
      "butikk": "Elkjøp",
      "beskriving": "Opptil 40% rabatt på mobiltelefoner under Vårsalget.",
      "kode": null,
      "utløper": null,
      "kjelde": "epost",
      "lagt_til": "2026-04-08"
    },
    {
      "id": "5ee759f0-7e97-45a9-aa15-3b009dc28e01",
      "butikk": "Elkjøp",
      "beskriving": "Gode priser på PC-er og mer under Vårsalget.",
      "kode": null,
      "utløper": null,
      "kjelde": "epost",
      "lagt_til": "2026-04-08"
    },
    {
      "id": "e63e4afb-b200-4c6b-8397-dfac71679a2e",
      "butikk": "Klint",
      "beskriving": "Tilbod på eit utval startprodukt (Starter Kit) via personleg lenke",
      "kode": "STARTERKIT",
      "utløper": null,
      "kjelde": "epost",
      "lagt_til": "2026-04-08"
    },
    {
      "id": "f7c6cfc8-f28a-41b0-aecc-2711d6178f54",
      "butikk": "MENY",
      "beskriving": "5% Trumf-bonus på netthandel",
      "kode": null,
      "utløper": null,
      "kjelde": "epost",
      "lagt_til": "2026-04-08"
    },
    {
      "id": "a3ff8422-e04f-4f04-8d1c-3afc8fa8a7fc",
      "butikk": "Georg Jensen Damask",
      "beskriving": "Sun Stripe badelagen og matchende tote bag til introduktionspris (290 DKK, normalpris 485 DKK)",
      "kode": null,
      "utløper": null,
      "kjelde": "epost",
      "lagt_til": "2026-04-08"
    },
    {
      "id": "8ea29fff-ebe8-4e50-8c91-eebc2d5219ce",
      "butikk": "Komplett Club",
      "beskriving": "Alltid fri frakt på rimeligste fraktalternativ til fastlands-Norge for medlemmer. Gjelder ikke hjemlevering med Porterbuddy.",
      "kode": null,
      "utløper": null,
      "kjelde": "epost",
      "lagt_til": "2026-04-09"
    },
    {
      "id": "8260080d-6c11-4407-a6d2-071131d4e8cc",
      "butikk": "Komplett Club",
      "beskriving": "Få 200 CLUB-poeng for hver produktanmeldelse du skriver.",
      "kode": null,
      "utløper": null,
      "kjelde": "epost",
      "lagt_til": "2026-04-09"
    },
    {
      "id": "63690163-a595-43ef-8bf3-4c2f653f416d",
      "butikk": "Komplett Club",
      "beskriving": "Tjen CLUB-poeng på alle kjøp du gjør som medlem.",
      "kode": null,
      "utløper": null,
      "kjelde": "epost",
      "lagt_til": "2026-04-09"
    },
    {
      "id": "67d65ff3-07f4-416a-ae78-61ec6d20d30e",
      "butikk": "Komplett Club",
      "beskriving": "Spar 10.000 på ny TV",
      "kode": null,
      "utløper": null,
      "kjelde": "epost",
      "lagt_til": "2026-04-09"
    },
    {
      "id": "623c2d30-3ac1-4b5e-a0b2-19ddd22d8889",
      "butikk": "Komplett Club",
      "beskriving": "Ukens tilbud",
      "kode": null,
      "utløper": null,
      "kjelde": "epost",
      "lagt_til": "2026-04-09"
    },
    {
      "id": "7a5cdebe-2749-425e-bcfe-9e5b90d2066b",
      "butikk": "Komplett Club",
      "beskriving": "Gaming deals",
      "kode": null,
      "utløper": null,
      "kjelde": "epost",
      "lagt_til": "2026-04-09"
    },
    {
      "id": "f094e17e-5611-4872-8557-2c8255f6aec1",
      "butikk": "Komplett Club",
      "beskriving": "Spar 2.000,- på Samsung Galaxy Tab S10 FE WiFi 128GB (grå)",
      "kode": null,
      "utløper": null,
      "kjelde": "epost",
      "lagt_til": "2026-04-09"
    },
    {
      "id": "f651fbce-05cc-4e1e-b43f-590ea7994196",
      "butikk": "Strawberry",
      "beskriving": "Forsalg på billetter til Manchester United Tour i Helsinki, Trondheim, Stockholm og Gøteborg.",
      "kode": null,
      "utløper": null,
      "kjelde": "epost",
      "lagt_til": "2026-04-09"
    },
    {
      "id": "efbc4b1f-7353-4189-84a1-71577378a028",
      "butikk": "Kid Interiør",
      "beskriving": "50% rabatt på gardiner, pynteputer og pledd til soverommet",
      "kode": null,
      "utløper": null,
      "kjelde": "epost",
      "lagt_til": "2026-04-09"
    },
    {
      "id": "3881e0d9-d9a9-4e1e-84b7-979d045e2b80",
      "butikk": "Barnas Hus",
      "beskriving": "-40% på alle parkdresser fra Reflex",
      "kode": null,
      "utløper": null,
      "kjelde": "epost",
      "lagt_til": "2026-04-09"
    },
    {
      "id": "504aec20-e165-4aec-9a4e-1e26eda58fdc",
      "butikk": "Clas Ohlson",
      "beskriving": "-20 % på rengjøringsprodukter fra Jif (klubbpris for medlemmer)",
      "kode": null,
      "utløper": null,
      "kjelde": "epost",
      "lagt_til": "2026-04-09"
    },
    {
      "id": "571370b0-c137-4fd9-bed5-3a1d2d9e1a70",
      "butikk": "Norwegian (via Spenn)",
      "beskriving": "Få 3x Spenn på alle ruter med Norwegian for reiser i perioden 07.04.26 - 30.08.26.",
      "kode": "SUPERSPENN",
      "utløper": null,
      "kjelde": "epost",
      "lagt_til": "2026-04-09"
    },
    {
      "id": "657ca546-5e19-4b88-b422-f204ac6b73cb",
      "butikk": "MENY",
      "beskriving": "5% Trumf-bonus på levering (netthandel)",
      "kode": null,
      "utløper": "2024-04-30",
      "kjelde": "epost",
      "lagt_til": "2026-04-09"
    }
  ]
}